datasci/__init__.py
datasci/notebook/__init__.py
datasci/notebook/init.py
datasci/pandas/__init__.py
datasci-0.4.0.dist-info/METADATA
datasci-0.4.0.dist-info/WHEEL
datasci-0.4.0.dist-info/top_level.txt
datasci-0.4.0.dist-info/RECORD
