Metadata-Version: 2.1
Name: datasci
Version: 0.4.0
Summary: Data science utilities
Home-page: https://github.com/chbrown/datasci-python
Author: Christopher Brown
Author-email: io@henrian.com
License: MIT
Platform: UNKNOWN
Classifier: Development Status :: 1 - Planning
Classifier: Intended Audience :: Science/Research
Classifier: Programming Language :: Python
Classifier: Topic :: Scientific/Engineering
Requires-Python: >=3.6
Requires-Dist: altair (>=2.2)
Requires-Dist: cytoolz (>=0.8)
Requires-Dist: ipython (>=6.5)
Requires-Dist: Markdown (>=2.6)
Requires-Dist: numpy (>=1.15)
Requires-Dist: pandas (>=0.23)
Requires-Dist: pyperclip (>=1.7.0)
Requires-Dist: scipy (>=1.1)
Requires-Dist: smart-open (>=1.8.1)
Requires-Dist: statsmodels (>=0.9)
